[
  {
    "className": "PLAYER_LEVEL",
    "props": [
      {
        "type": 3,
        "strVal": "rank_004",
        "name": "NAME"
      },
      {
        "type": 1,
        "intVal": 4,
        "name": "LEVEL_INDEX"
      },
      {
        "type": 1,
        "intVal": 4000,
        "name": "XP_UNLOCK"
      },
      {
        "type": 7,
        "strList": [],
        "name": "ITEMS_RECIEVED"
      },
      {
        "type": 7,
        "strList": [],
        "name": "ITEMS_UNLOCKED"
      }
    ],
    "name": "rank_004",
    "parents": []
  }
]